prometheus_http_client/__init__.py
prometheus_http_client/exporter/__init__.py
prometheus_http_client/exporter/consul_exporter.py
prometheus_http_client/exporter/exporter.py
prometheus_http_client/exporter/memcached_exporter.py
prometheus_http_client/exporter/mysqld_exporter.py
prometheus_http_client/exporter/node_exporter.py
prometheus_http_client/prometheus/__init__.py
prometheus_http_client/prometheus/client.py
prometheus_http_client/provider/__init__.py
prometheus_http_client/provider/core.py
prometheus_http_client-1.0.0.dist-info/DESCRIPTION.rst
prometheus_http_client-1.0.0.dist-info/METADATA
prometheus_http_client-1.0.0.dist-info/RECORD
prometheus_http_client-1.0.0.dist-info/WHEEL
prometheus_http_client-1.0.0.dist-info/metadata.json
prometheus_http_client-1.0.0.dist-info/top_level.txt
