Metadata-Version: 1.0
Name: prometheus-http-client
Version: 1.0.0
Summary: Prometheus service http client, author liyuanjun
Home-page: https://github.com/tomoncle/prometheus-http-client
Author: liyuanjun
Author-email: 1123431949@qq.com
License: MIT
Platform: UNKNOWN
